LICENSE
README.md
setup.py
cornell/__init__.py
cornell/_version.py
cornell/cornell_helpers.py
cornell/cornell_server.py
cornell/custom_matchers.py
cornell/signals.py
cornell/vcr_settings.py
cornell.egg-info/PKG-INFO
cornell.egg-info/SOURCES.txt
cornell.egg-info/dependency_links.txt
cornell.egg-info/entry_points.txt
cornell.egg-info/requires.txt
cornell.egg-info/top_level.txt
tests/__init__.py
tests/conftest.py
tests/test_get_custom_vcr.py
tests/test_odata_query_processing.py
tests/test_record_and_replay.py
tests/test_record_errors.py
tests/test_request_path.py
tests/test_signals.py
tests/test_soap_processing.py
tests/test_vcr_dir.py