Metadata-Version: 2.1
Name: cornell
Version: 1.1.0
Summary: Cornell: record & replay mock server
Home-page: https://hiredscorelabs.github.io/cornell/
Author: Yael Mintz
Author-email: yaelmi3@gmail.com
License: MIT
Project-URL: Documentation, https://hiredscorelabs.github.io/cornell/
Project-URL: Source, https://github.com/hiredscorelabs/cornell
Platform: UNKNOWN
Provides-Extra: dev
